esahub/__init__.py
esahub/check.py
esahub/checksum.py
esahub/cli.py
esahub/config.py
esahub/config.yaml
esahub/geo.py
esahub/main.py
esahub/scihub.py
esahub/tty.py
esahub/utils.py
esahub/tests/__init__.py
esahub/tests/config.py
esahub/tests/test_all.py
esahub_wegaw-0.1.1.dist-info/LICENSE.txt
esahub_wegaw-0.1.1.dist-info/METADATA
esahub_wegaw-0.1.1.dist-info/WHEEL
esahub_wegaw-0.1.1.dist-info/entry_points.txt
esahub_wegaw-0.1.1.dist-info/top_level.txt
esahub_wegaw-0.1.1.dist-info/RECORD
