Metadata-Version: 2.1
Name: esahub-wegaw
Version: 0.1.1
Summary: A Python module for downloading ESA satellite data, based on esahub
Home-page: https://github.com/wegaw/esahub
Author: Gonzalo Alvarez
Author-email: gonzalo.alvarez@wegaw.com
License: MIT
Keywords: esahub,scihub,sentinel,satellite,copernicus
Platform: UNKNOWN
Classifier: Intended Audience :: Science/Research
Classifier: Intended Audience :: Developers
Classifier: Natural Language :: English
Classifier: Programming Language :: Python
Classifier: Programming Language :: Python :: 3.5
Classifier: Programming Language :: Python :: 3.6
Classifier: Programming Language :: Python :: 3.7
License-File: LICENSE.txt
Requires-Dist: aiohttp
Requires-Dist: lxml
Requires-Dist: numpy
Requires-Dist: python-dateutil
Requires-Dist: pytz
Requires-Dist: pyyaml
Requires-Dist: shapely
Requires-Dist: tqdm
